asciidoc_table_width_adjuster/__init__.py
asciidoc_table_width_adjuster/main.py
column_width-0.1.0.dist-info/METADATA
column_width-0.1.0.dist-info/WHEEL
column_width-0.1.0.dist-info/top_level.txt
column_width-0.1.0.dist-info/RECORD
