Metadata-Version: 2.4
Name: column-width
Version: 0.1.0
Summary: Add your description here
Home-page: https://github.com/yourusername/column-width
Author: Puneet Bajaj
Author-email: bajajpuneet223@gmail.com
Requires-Python: >=3.6
Dynamic: author
Dynamic: author-email
Dynamic: home-page
Dynamic: requires-python
